OBJECTIVE:

- Сократи ответ до минимум одного, максимум трёх предложений. Это должен быть быстрый ответ на собеседовании (его можно
  заучить и он должен быть
  верным).

DATA:


# *Comprehensions и генераторные выражения*

## **Junior Level**

Comprehensions и генераторные выражения — это лаконичные конструкции в Python для создания коллекций на основе итераций.
Представьте, что вам нужно преобразовать один список в другой: вместо написания многострочного цикла `for` можно
использовать одну строку с comprehension.

List comprehension (списковое включение) создаёт новый список: `[x*2 for x in range(5)]` даст `[0, 2, 4, 6, 8]`. Set
comprehension создаёт множество, dict comprehension — словарь. Генераторное выражение выглядит похоже, но в круглых
скобках: `(x*2 for x in range(5))`. Разница в том, что генераторное выражение не создаёт коллекцию сразу, а возвращает
итератор, который вычисляет элементы «лениво», по одному, что экономит память при работе с большими объёмами данных.

Их удобно использовать для фильтрации (добавив `if`) и для преобразования элементов. Это делает код чище и часто
быстрее, чем аналогичные циклы.

## **Middle Level**

1. **Типы comprehensions**:

- List comprehension: `[выражение for элемент in итератор]`
- Set comprehension: `{выражение for элемент in итератор}`
- Dict comprehension: `{ключ: значение for элемент in итератор}`
- Generator expression: `(выражение for элемент in итератор)`

2. **Синтаксические возможности**:

- Могут содержать несколько циклов `for`: `[x+y for x in list1 for y in list2]`
- Поддерживают условия фильтрации `if`: `[x for x in range(10) if x % 2 == 0]`
- Условия могут быть вложенными и комбинированными

3. **Область видимости**: Начиная с Python 3, comprehensions и генераторные выражения выполняются в собственной области
   видимости. Переменные, созданные внутри (например, переменная цикла), не «просачиваются» наружу, что предотвращает
   случайные перезаписи.

4. **Производительность**: List comprehensions обычно выполняются быстрее эквивалентных циклов `for`, потому что они
   оптимизированы на уровне байткода и выполняют операции добавления элементов напрямую, минуя вызовы методов.
   Генераторные выражения экономят память, но имеют небольшие накладные расходы на каждый вызов `next()`.

5. **Ленивые вычисления**: Генераторные выражения вычисляют элементы только когда они запрашиваются (например, в цикле
   `for` или при вызове `next()`). Это позволяет работать с бесконечными последовательностями и потоками данных.

6. **Отличия от функций-генераторов**: Генераторные выражения — это синтаксический сахар для создания анонимных
   генераторов. Они не могут содержать сложную логику с несколькими `yield` или `return`, в отличие от
   функций-генераторов.

## **Senior Level**

1. **Компиляция comprehensions**:

В CPython каждое comprehension компилируется во **временную функцию**. Например, list comprehension
`[x*2 for x in iterable]` преобразуется в скрытую функцию, которая создаёт список, выполняет цикл и возвращает
результат.

Байткод для вызова list comprehension:

```
LOAD_CONST               <code object <listcomp> at 0x...>
LOAD_CONST               '<listcomp>'
MAKE_FUNCTION            0
LOAD_GLOBAL              iterable
GET_ITER
CALL_FUNCTION            1
```

Объект кода `<listcomp>` содержит байткод, реализующий логику comprehension.

2. **Внутренняя функция comprehension**:

Байткод внутренней функции для `[x*2 for x in range(5)]`:

```
0 BUILD_LIST               0       # Создаём пустой список
2 LOAD_FAST                0 (.0)  # Загружаем итератор
4 FOR_ITER                16 (to 22)
6 STORE_FAST               1 (x)   # Сохраняем текущий элемент в x
8 LOAD_FAST                1 (x)
10 LOAD_CONST               0 (2)
12 BINARY_MULTIPLY
14 LIST_APPEND              2       # Добавляем результат в список
16 JUMP_ABSOLUTE            4
18 POP_BLOCK
20 RETURN_VALUE
```

Ключевая инструкция `LIST_APPEND` (код 0x69) добавляет элемент напрямую во внутренний массив списка, что быстрее, чем
вызов метода `append()`.

3. **Генераторные выражения**:

Генераторное выражение `(x*2 for x in range(5))` компилируется в код, создающий объект генератора. Внутренняя функция
`<genexpr>` использует `YIELD_VALUE`:

```
0 LOAD_FAST                0 (.0)
2 FOR_ITER                12 (to 16)
4 STORE_FAST               1 (x)
6 LOAD_FAST                1 (x)
8 LOAD_CONST               0 (2)

10 BINARY_MULTIPLY
12 YIELD_VALUE # Возвращаем значение и приостанавливаемся
14 JUMP_ABSOLUTE 2
16 LOAD_CONST 1 (None)
18 RETURN_VALUE

```

При каждом вызове `next()` выполнение возобновляется с точки после последнего `YIELD_VALUE`.

4. **Специализированные инструкции байткода**:

Для каждого типа comprehension есть своя инструкция добавления элемента:

- `LIST_APPEND` (0x69) для list comprehensions
- `SET_ADD` (0x67) для set comprehensions
- `MAP_ADD` (0x68) для dict comprehensions

Эти инструкции работают напрямую с внутренними структурами данных (`PyListObject`, `PySetObject`, `PyDictObject`), минуя
вызовы методов Python.

5. **Оптимизации CPython**:

- **Предварительное выделение памяти**: Если итерируемый объект имеет метод `__len__`, CPython использует его для
  предварительного выделения памяти под список, уменьшая количество перераспределений.
- **Инлайн-кэширование**: В Python 3.11+ добавлен адаптивный байткод, который кэширует частые операции внутри
  comprehensions.
- **Оптимизация стека**: Внутренние переменные comprehension хранятся в массиве `f_localsplus` фрейма, а не в словаре,
  что ускоряет доступ.

6. **Области видимости и cell variables**:

Если comprehension использует переменные из внешней области видимости, они захватываются через cell objects. Например, в
`[x*y for x in range(3)]`, если `y` — внешняя переменная, она загружается инструкцией `LOAD_DEREF` из cell object.

7. **Производительность: comprehension vs цикл**:

List comprehension быстрее цикла с `append()` по трём причинам:

1. Операция добавления выполняется нативным кодом в `LIST_APPEND`
2. Нет накладных расходов на поиск и вызов метода `append`
3. Весь цикл выполняется в одной области видимости без переключения контекста

8. **Генераторные выражения и память**:

Генераторные выражения создают объект типа `PyGenObject`, который содержит фрейм выполнения. Этот фрейм сохраняет
состояние между вызовами `next()`. Память освобождается только после завершения итерации или явного вызова `close()`.

9. **Вложенные comprehensions**:

Вложенное comprehension `[[i*j for j in range(3)] for i in range(4)]` компилируется в две внутренние функции. Внешняя
функция создаёт внешний список, внутренняя — внутренние списки. Это может создавать дополнительные накладные расходы
из-за создания множества временных объектов.

10. **Словарные comprehension**:

Dict comprehension `{x: x**2 for x in range(5)}` использует инструкцию `MAP_ADD`, которая добавляет пару ключ-значение
напрямую в хеш-таблицу словаря. Это быстрее, чем вызов `dict.__setitem__`.

11. **Особенности множественных comprehension**:

Set comprehension использует `SET_ADD`, который проверяет уникальность элемента через хеш-таблицу множества. При
дублировании элементов выполняется лишняя работа, но результат остаётся корректным.

12. **Потенциальные проблемы**:

- **Утечка памяти в генераторах**: Если генераторное выражение не итерируется до конца (например, из-за `break`), его
  фрейм может остаться в памяти до сборки мусора.
- **Неправильный порядок вложенных циклов**: В comprehension вида `[x+y for x in A for y in B]` сначала фиксируется `x`,
  затем итерируется `y`. Это противоположно вложенным циклам `for x in A: for y in B:`.
- **Оценка условий**: Условия `if` оцениваются для каждого элемента, что может быть дорого, если условие сложное.

13. **Тестирование для AQA**:

При тестировании кода с comprehensions и генераторными выражениями важно:

- Проверять корректность выходных данных для всех типов входных данных (пустые, большие, с дубликатами)
- Измерять потребление памяти при использовании генераторных выражений
- Тестировать производительность на больших наборах данных
- Проверять обработку исключений внутри выражений
- Убеждаться, что генераторные выражения не используются повторно (они одноразовые)
- Проверять корректность работы с замыканиями

- [Содержание](#содержание)